[
    {
        "img":"https://assets.firestonecompleteautocare.com/content/dam/bsro-sites/global/images/tires/full-60/h175/PotenzaRE92.png",
        "brand":"BRIDGESTONE",
        "tirename":"BRIDGESTONE POTENZA RE92",
        "stability":"Stability: 9.1",
        "traction":"Traction: 8.1",
        "noice":"Noise Level: 8.3"
    },
    {
        "img":"https://assets.firestonecompleteautocare.com/content/dam/bsro-sites/global/images/tires/full-60/h175/PotenzaRE92.png",
        "brand":"BRIDGESTONE",
        "tirename":"BRIDGESTONE TURANZA EL42",
        "stability":"Stability: 8.9",
        "traction":"Traction: 8.3",
        "noice":"Noise Level: 8.9"
    },
    {
        "img":"https://assets.firestonecompleteautocare.com/content/dam/bsro-sites/global/images/tires/full-60/h175/PotenzaRE92.png",
        "brand":"BRIDGESTONE",
        "tirename":"BRIDGESTONE TURANZA ER33",
        "stability":"Stability: 0",
        "traction":"Traction: 0",
        "noice":"Noise Level: 9"
    },
    {
        "img":"https://assets.firestonecompleteautocare.com/content/dam/bsro-sites/global/images/tires/full-60/h175/PotenzaRE92.png",
        "brand":"FIRESTONE",
        "tirename":"FIRESTONE FIREHAWK GT",
        "stability":"Stability: 8.4",
        "traction":"Traction: 7.5",
        "noice":"Noise Level: 7.6"
    },
    {
        "img":"https://assets.firestonecompleteautocare.com/content/dam/bsro-sites/global/images/tires/full-60/h175/PotenzaRE92.png",
        "brand":"BRIDGESTONE",
        "tirename":"BRIDGESTONE R265",
        "stability":"Stability: 10",
        "traction":"Traction: 7",
        "noice":"Noise Level: 8.4"
    },
    {
        "img":"https://assets.firestonecompleteautocare.com/content/dam/bsro-sites/global/images/tires/full-60/h175/PotenzaRE92.png",
        "brand":"FIRESTONE",
        "tirename":"FIRESTONE TRANSFORCE HT",
        "stability":"Stability: 8.3",
        "traction":"Traction: 7.8",
        "noice":"Noise Level: 10"
    },
    {
        "img":"https://assets.firestonecompleteautocare.com/content/dam/bsro-sites/global/images/tires/full-60/h175/PotenzaRE92.png",
        "brand":"FIRESTONE",
        "tirename":"FIRESTONE DESTINATION A/T",
        "stability":"Stability: 8.6",
        "traction":"Traction: 8.3",
        "noice":"Noise Level: 8.4"
    },
    {
        "img":"https://assets.firestonecompleteautocare.com/content/dam/bsro-sites/global/images/tires/full-60/h175/PotenzaRE92.png",
        "brand":"FIRESTONE",
        "tirename":"FIRESTONE TRANSFORCE A/T",
        "stability":"Stability: 8.8",
        "traction":"Traction: 8",
        "noice":"Noise Level: 8.3"
    },
    {
        "img":"https://assets.firestonecompleteautocare.com/content/dam/bsro-sites/global/images/tires/full-60/h175/PotenzaRE92.png",
        "brand":"BRIDGESTONE",
        "tirename":"BRIDGESTONE DUELER H/P SPORT",
        "stability":"Stability: 7.8",
        "traction":"Traction: 8",
        "noice":"Noise Level: 6.8"
    },
    {
        "img":"https://assets.firestonecompleteautocare.com/content/dam/bsro-sites/global/images/tires/full-60/h175/PotenzaRE92.png",
        "brand":"FIRESTONE",
        "tirename":"FIRESTONE FR710",
        "stability":"Stability: 8.6",
        "traction":"Traction: 7.9",
        "noice":"Noise Level: 9.2"
    },
    {
        "img":"https://assets.firestonecompleteautocare.com/content/dam/bsro-sites/global/images/tires/full-60/h175/PotenzaRE92.png",
        "brand":"BRIDGESTONE",
        "tirename":"BRIDGESTONE DURAVIS R500 HD",
        "stability":"Stability: 8.2",
        "traction":"Traction: 8.9",
        "noice":"Noise Level: 8"
    },
    {
        "img":"https://assets.firestonecompleteautocare.com/content/dam/bsro-sites/global/images/tires/full-60/h175/PotenzaRE92.png",
        "brand":"BRIDGESTONE",
        "tirename":"BRIDGESTONE POTENZA RE050A RFT",
        "stability":"Stability: 8.6",
        "traction":"Traction: 9.9",
        "noice":"Noise Level: 8.2"
    },
    {
        "img":"https://assets.firestonecompleteautocare.com/content/dam/bsro-sites/global/images/tires/full-60/h175/PotenzaRE92.png",
        "brand":"PRIMEWELL",
        "tirename":"PRIMEWELL VALERA H/T",
        "stability":"Stability: 8.7",
        "traction":"Traction: 7.7",
        "noice":"Noise Level: 9.2"
    },
    {
        "img":"https://assets.firestonecompleteautocare.com/content/dam/bsro-sites/global/images/tires/full-60/h175/PotenzaRE92.png",
        "brand":"FIRESTONE",
        "tirename":"FIRESTONE AFFINITY TOURING S4 FF",
        "stability":"Stability: 7",
        "traction":"Traction: 9.9",
        "noice":"Noise Level: 8.2"
    }, {
        "img":"https://assets.firestonecompleteautocare.com/content/dam/bsro-sites/global/images/tires/full-60/h175/PotenzaRE92.png",
        "brand":"BRIDGESTONE",
        "tirename":"BRIDGESTONE BLIZZAK LM-32",
        "stability":"Stability: 7.6",
        "traction":"Traction: 9.9",
        "noice":"Noise Level: 5.2"
    },
    {
        "img":"https://assets.firestonecompleteautocare.com/content/dam/bsro-sites/global/images/tires/full-60/h175/PotenzaRE92.png",
        "brand":"FIRESTONE",
        "tirename":"FIRESTONE DESTINATION LE2",
        "stability":"Stability: 6",
        "traction":"Traction: 9",
        "noice":"Noise Level: 7.2"
    },
    {
        "img":"https://assets.firestonecompleteautocare.com/content/dam/bsro-sites/global/images/tires/full-60/h175/PotenzaRE92.png",
        "brand":"FIRESTONE",
        "tirename":"FIRESTONE FT140",
        "stability":"Stability: 8.6",
        "traction":"Traction: 7.9",
        "noice":"Noise Level: 9.2"
    },
    {
        "img":"https://assets.firestonecompleteautocare.com/content/dam/bsro-sites/global/images/tires/full-60/h175/PotenzaRE92.png",
        "brand":"BRIDGESTONE",
        "tirename":"BRIDGESTONE TURANZA EL440",
        "stability":"Stability: 8.9",
        "traction":"Traction: 7.9",
        "noice":"Noise Level: 8"
    },
    {
        "img":"https://assets.firestonecompleteautocare.com/content/dam/bsro-sites/global/images/tires/full-60/h175/PotenzaRE92.png",
        "brand":"FIRESTONE",
        "tirename":"FIRESTONE FIREHAWK INDY 500",
        "stability":"Stability: 8.3",
        "traction":"Traction: 7.9",
        "noice":"Noise Level: 8.2"
    },
    {
        "img":"https://assets.firestonecompleteautocare.com/content/dam/bsro-sites/global/images/tires/full-60/h175/PotenzaRE92.png",
        "brand":"FIRESTONE",
        "tirename":"FIRESTONE FIREHAWK INDY 500",
        "stability":"Stability: 8.3",
        "traction":"Traction: 7.9",
        "noice":"Noise Level: 8.2"
    },
    {
        "img":"https://assets.firestonecompleteautocare.com/content/dam/bsro-sites/global/images/tires/full-60/h175/PotenzaRE92.png",
        "brand":"SUREDRIVE",
        "tirename":"Economy Tires",
        "stability":"Stability: 0",
        "traction":"Traction: 8",
        "noice":"Noise Level: 7"
    },
    {
        "img":"https://assets.firestonecompleteautocare.com/content/dam/bsro-sites/global/images/tires/full-60/h175/PotenzaRE92.png",
        "brand":"SUREDRIVE",
        "tirename":"All Terrain Tires",
        "stability":"Stability: 6",
        "traction":"Traction: 4",
        "noice":"Noise Level: 8"
    },
    {
        "img":"https://assets.firestonecompleteautocare.com/content/dam/bsro-sites/global/images/tires/full-60/h175/PotenzaRE92.png",
        "brand":"SUREDRIVE",
        "tirename":"All Terrain Tires",
        "stability":"Stability: 5",
        "traction":"Traction: 4",
        "noice":"Noise Level: 8"
    },
    {
        "img":"https://assets.firestonecompleteautocare.com/content/dam/bsro-sites/global/images/tires/full-60/h175/PotenzaRE92.png",
        "brand":"SUREDRIVE",
        "tirename":"Highway Tires",
        "stability":"Stability: 0",
        "traction":"Traction: 4",
        "noice":"Noise Level: 4"
    },
    {
        "img":"https://assets.firestonecompleteautocare.com/content/dam/bsro-sites/global/images/tires/full-60/h175/PotenzaRE92.png",
        "brand":"TOYO TIRES",
        "tirename":"Highway All-Season Tires",
        "stability":"Stability: 0",
        "traction":"Traction: 7",
        "noice":"Noise Level: 6"
    },
    {
        "img":"https://assets.firestonecompleteautocare.com/content/dam/bsro-sites/global/images/tires/full-60/h175/PotenzaRE92.png",
        "brand":"TOYO TIRES",
        "tirename":"Highway All-Season Tires",
        "stability":"Stability: 0",
        "traction":"Traction: 8",
        "noice":"Noise Level: 8"
    },
    {
        "img":"https://assets.firestonecompleteautocare.com/content/dam/bsro-sites/global/images/tires/full-60/h175/PotenzaRE92.png",
        "brand":"TOYO TIRES",
        "tirename":"Highway All-Season Tires",
        "stability":"Stability: 0",
        "traction":"Traction: 6",
        "noice":"Noise Level: 6"
    },
    {
        "img":"https://assets.firestonecompleteautocare.com/content/dam/bsro-sites/global/images/tires/full-60/h175/PotenzaRE92.png",
        "brand":"TOYO TIRES",
        "tirename":"Ultra High Performance All Season Tires",
        "stability":"Stability: 0",
        "traction":"Traction: 7",
        "noice":"Noise Level: 8"
    },
    {
        "img":"https://assets.firestonecompleteautocare.com/content/dam/bsro-sites/global/images/tires/full-60/h175/PotenzaRE92.png",
        "brand":"TOYO TIRES",
        "tirename":"Ultra High Performance All Season Tires",
        "stability":"Stability: 0",
        "traction":"Traction: 7",
        "noice":"Noise Level: 6"
    },
    {
        "img":"https://assets.firestonecompleteautocare.com/content/dam/bsro-sites/global/images/tires/full-60/h175/PotenzaRE92.png",
        "brand":"TOYO TIRES",
        "tirename":"Max Traction Tires",
        "stability":"Stability: 0",
        "traction":"Traction: 9",
        "noice":"Noise Level: 7"
    },
    {
        "img":"https://assets.firestonecompleteautocare.com/content/dam/bsro-sites/global/images/tires/full-60/h175/PotenzaRE92.png",
        "brand":"TOYO TIRES",
        "tirename":"Max Traction Tires",
        "stability":"Stability: 0",
        "traction":"Traction: 7",
        "noice":"Noise Level: 6"
    },
    {
        "img":"https://assets.firestonecompleteautocare.com/content/dam/bsro-sites/global/images/tires/full-60/h175/PotenzaRE92.png",
        "brand":"PRIMEWELL",
        "tirename":"Max Traction Tires",
        "stability":"Stability: 0",
        "traction":"Traction: 7",
        "noice":"Noise Level: 6"
    },
    {
        "img":"https://assets.firestonecompleteautocare.com/content/dam/bsro-sites/global/images/tires/full-60/h175/PotenzaRE92.png",
        "brand":"PRIMEWELL",
        "tirename":"Max Traction Tires",
        "stability":"Stability: 0",
        "traction":"Traction: 7",
        "noice":"Noise Level: 6"
    },
    {
        "img":"https://assets.firestonecompleteautocare.com/content/dam/bsro-sites/global/images/tires/full-60/h175/PotenzaRE92.png",
        "brand":"PRIMEWELL",
        "tirename":"Max Traction Tires",
        "stability":"Stability: 0",
        "traction":"Traction: 7",
        "noice":"Noise Level: 6"
    },
    {
        "img":"https://assets.firestonecompleteautocare.com/content/dam/bsro-sites/global/images/tires/full-60/h175/PotenzaRE92.png",
        "brand":"PRIMEWELL",
        "tirename":"Max Traction Tires",
        "stability":"Stability: 0",
        "traction":"Traction: 7",
        "noice":"Noise Level: 6"
    },
    {
        "img":"https://assets.firestonecompleteautocare.com/content/dam/bsro-sites/global/images/tires/full-60/h175/PotenzaRE92.png",
        "brand":"PRIMEWELL",
        "tirename":"Max Traction Tires",
        "stability":"Stability: 0",
        "traction":"Traction: 7",
        "noice":"Noise Level: 6"
    }

]